Metadata-Version: 1.1
Name: simpleoskali
Version: 0.0.1
Summary: SimpleOS for Kali Linux Terminal
Home-page: UNKNOWN
Author: Ilia Kalygin
Author-email: UNKNOWN
License: MIT
Keywords: simpleoskali
Platform: UNKNOWN
Classifier: Development Status :: 5 - Production/Stable
Classifier: Intended Audience :: Education
Classifier: Operating System :: Microsoft :: Windows :: Windows 10
Classifier: License :: OSI Approved :: MIT License
Classifier: Programming Language :: Python :: 3
